Metadata-Version: 2.1
Name: counter-solo-elements
Version: 0.0.1
Summary: Tells how many elements are found only 1 time
Home-page: https://git.foxminded.ua/foxstudent105136/task-4/-/merge_requests/2
Author: OlexandrTsubera
Author-email: bolshoygrizli@gmail.com
License: UNKNOWN
Platform: UNKNOWN
